llama_stack/__init__.py
llama_stack/env.py
llama_stack/log.py
llama_stack/cli/__init__.py
llama_stack/cli/llama.py
llama_stack/cli/subcommand.py
llama_stack/cli/table.py
llama_stack/cli/utils.py
llama_stack/cli/scripts/__init__.py
llama_stack/cli/scripts/install-wheel-from-presigned.sh
llama_stack/cli/scripts/run.py
llama_stack/cli/stack/__init__.py
llama_stack/cli/stack/_list_deps.py
llama_stack/cli/stack/list_apis.py
llama_stack/cli/stack/list_deps.py
llama_stack/cli/stack/list_providers.py
llama_stack/cli/stack/list_stacks.py
llama_stack/cli/stack/remove.py
llama_stack/cli/stack/run.py
llama_stack/cli/stack/stack.py
llama_stack/cli/stack/utils.py
llama_stack/core/__init__.py
llama_stack/core/admin.py
llama_stack/core/build.py
llama_stack/core/client.py
llama_stack/core/common.sh
llama_stack/core/configure.py
llama_stack/core/datatypes.py
llama_stack/core/distribution.py
llama_stack/core/external.py
llama_stack/core/id_generation.py
llama_stack/core/inspect.py
llama_stack/core/library_client.py
llama_stack/core/providers.py
llama_stack/core/request_headers.py
llama_stack/core/resolver.py
llama_stack/core/stack.py
llama_stack/core/start_stack.sh
llama_stack/core/testing_context.py
llama_stack/core/access_control/__init__.py
llama_stack/core/access_control/access_control.py
llama_stack/core/access_control/conditions.py
llama_stack/core/access_control/datatypes.py
llama_stack/core/conversations/__init__.py
llama_stack/core/conversations/conversations.py
llama_stack/core/prompts/__init__.py
llama_stack/core/prompts/prompts.py
llama_stack/core/routers/__init__.py
llama_stack/core/routers/datasets.py
llama_stack/core/routers/eval_scoring.py
llama_stack/core/routers/inference.py
llama_stack/core/routers/safety.py
llama_stack/core/routers/tool_runtime.py
llama_stack/core/routers/vector_io.py
llama_stack/core/routing_tables/__init__.py
llama_stack/core/routing_tables/benchmarks.py
llama_stack/core/routing_tables/common.py
llama_stack/core/routing_tables/datasets.py
llama_stack-0.4.4.dist-info/licenses/LICENSE
llama_stack-0.4.4.dist-info/METADATA
llama_stack-0.4.4.dist-info/WHEEL
llama_stack-0.4.4.dist-info/entry_points.txt
llama_stack-0.4.4.dist-info/top_level.txt
llama_stack-0.4.4.dist-info/RECORD
