Metadata-Version: 2.4
Name: llama_stack
Version: 0.4.4
Summary: Llama Stack
Author-email: Meta Llama <llama-oss@meta.com>
License: MIT
Project-URL: Homepage, https://github.com/llamastack/llama-stack
Classifier: License :: OSI Approved :: MIT License
Classifier: Programming Language :: Python :: 3
Classifier: Operating System :: OS Independent
Classifier: Intended Audience :: Developers
Classifier: Intended Audience :: Information Technology
Classifier: Intended Audience :: Science/Research
Classifier: Topic :: Scientific/Engineering :: Artificial Intelligence
Classifier: Topic :: Scientific/Engineering :: Information Analysis
Requires-Python: >=3.12
License-File: LICENSE
Requires-Dist: PyYAML>=6.0
Requires-Dist: aiohttp>=3.13.3
Requires-Dist: fastapi<1.0,>=0.115.0
Requires-Dist: fire
Requires-Dist: httpx
Requires-Dist: jinja2>=3.1.6
Requires-Dist: jsonschema
Requires-Dist: llama-stack-api
Requires-Dist: openai>=2.5.0
Requires-Dist: prompt-toolkit
Requires-Dist: python-dotenv
Requires-Dist: pyjwt[crypto]>=2.10.0
Requires-Dist: pydantic>=2.11.9
Requires-Dist: rich
Requires-Dist: termcolor
Requires-Dist: tiktoken
Requires-Dist: pillow
Requires-Dist: h11>=0.16.0
Requires-Dist: python-multipart>=0.0.20
Requires-Dist: uvicorn>=0.34.0
Requires-Dist: opentelemetry-sdk>=1.30.0
Requires-Dist: opentelemetry-exporter-otlp-proto-http>=1.30.0
Requires-Dist: aiosqlite>=0.21.0
Requires-Dist: asyncpg
Requires-Dist: sqlalchemy[asyncio]>=2.0.41
Requires-Dist: starlette>=0.49.1
Requires-Dist: psycopg2-binary
Requires-Dist: tornado>=6.5.3
Requires-Dist: urllib3>=2.6.3
Provides-Extra: client
Requires-Dist: llama-stack-client==0.4.4; extra == "client"
Dynamic: license-file
